[
  {
    "id": "jr3u7bi7vmor9l13c",
    "name": "Тімоха",
    "avatar": "💎",
    "color": "#2196F3",
    "isChild": true,
    "words": [
      {
        "id": "a17t7r1pjmor9l13c",
        "english": "hello",
        "ukrainian": "привіт",
        "addedDate": "2026-05-04",
        "timesStudied": 10,
        "timesKnown": 10,
        "timesUnknown": 0,
        "category": "easy",
        "streak": 2
      },
      {
        "id": "dqvvktvpmmor9l13c",
        "english": "apple",
        "ukrainian": "яблуко",
        "addedDate": "2026-05-04",
        "timesStudied": 10,
        "timesKnown": 10,
        "timesUnknown": 0,
        "category": "easy",
        "streak": 2
      },
      {
        "id": "1ox1wbntvmor9l13c",
        "english": "cat",
        "ukrainian": "кіт",
        "addedDate": "2026-05-04",
        "timesStudied": 9,
        "timesKnown": 9,
        "timesUnknown": 0,
        "category": "easy",
        "streak": 2
      },
      {
        "id": "mdt77iqrnmor9l13c",
        "english": "dog",
        "ukrainian": "собака",
        "addedDate": "2026-05-04",
        "timesStudied": 9,
        "timesKnown": 9,
        "timesUnknown": 0,
        "category": "easy",
        "streak": 2
      },
      {
        "id": "tse68hr0zmor9l13c",
        "english": "school",
        "ukrainian": "школа",
        "addedDate": "2026-05-04",
        "timesStudied": 26,
        "timesKnown": 15,
        "timesUnknown": 11,
        "category": "learning",
        "streak": 1
      },
      {
        "id": "sazdc0x8hmor9ns3k",
        "english": "I",
        "ukrainian": "я",
        "addedDate": "2026-05-04",
        "timesStudied": 17,
        "timesKnown": 14,
        "timesUnknown": 3,
        "category": "easy",
        "streak": 0
      },
      {
        "id": "zwkpk7eyjmordoctf",
        "english": "ruler",
        "ukrainian": "лінійка",
        "addedDate": "2026-05-04",
        "timesStudied": 18,
        "timesKnown": 15,
        "timesUnknown": 3,
        "category": "learning",
        "streak": 4,
        "listed": true
      },
      {
        "id": "0u2yaaefamordoq01",
        "english": "pencil",
        "ukrainian": "олівець",
        "addedDate": "2026-05-04",
        "timesStudied": 9,
        "timesKnown": 9,
        "timesUnknown": 0,
        "category": "easy",
        "streak": 2
      },
      {
        "id": "fr2tllkkwmordozf0",
        "english": "book",
        "ukrainian": "книга",
        "addedDate": "2026-05-04",
        "timesStudied": 10,
        "timesKnown": 10,
        "timesUnknown": 0,
        "category": "easy",
        "streak": 2
      },
      {
        "id": "8hxmu3fwzmordpg30",
        "english": "boy",
        "ukrainian": "хлопчик",
        "addedDate": "2026-05-04",
        "timesStudied": 15,
        "timesKnown": 13,
        "timesUnknown": 2,
        "category": "easy",
        "streak": 0
      },
      {
        "id": "waj8p7t46mordpn9f",
        "english": "girl",
        "ukrainian": "дівчинка",
        "addedDate": "2026-05-04",
        "timesStudied": 22,
        "timesKnown": 16,
        "timesUnknown": 6,
        "category": "learning",
        "streak": 1
      },
      {
        "id": "bgpgmki32more4p68",
        "english": "chair",
        "ukrainian": "стул",
        "addedDate": "2026-05-04",
        "timesStudied": 12,
        "timesKnown": 10,
        "timesUnknown": 2,
        "category": "easy",
        "streak": 0
      },
      {
        "id": "tudgu3jl0more4p68",
        "english": "table",
        "ukrainian": "стіл",
        "addedDate": "2026-05-04",
        "timesStudied": 14,
        "timesKnown": 12,
        "timesUnknown": 2,
        "category": "easy",
        "streak": 0
      },
      {
        "id": "njitu5nx5more4p68",
        "english": "clock",
        "ukrainian": "годинник",
        "addedDate": "2026-05-04",
        "timesStudied": 16,
        "timesKnown": 13,
        "timesUnknown": 3,
        "category": "learning",
        "streak": 5,
        "listed": true
      },
      {
        "id": "hpxbkoz8zmore4p68",
        "english": "computer",
        "ukrainian": "компʼютер",
        "addedDate": "2026-05-04",
        "timesStudied": 8,
        "timesKnown": 8,
        "timesUnknown": 0,
        "category": "easy",
        "streak": 1
      },
      {
        "id": "kqbnc2ozimorekaw1",
        "english": "read",
        "ukrainian": "читати",
        "addedDate": "2026-05-04",
        "timesStudied": 29,
        "timesKnown": 10,
        "timesUnknown": 19,
        "category": "learning",
        "streak": 0,
        "listed": false
      },
      {
        "id": "ftb0ldb7xmorekaw1",
        "english": "write",
        "ukrainian": "писати",
        "addedDate": "2026-05-04",
        "timesStudied": 37,
        "timesKnown": 10,
        "timesUnknown": 27,
        "category": "hard",
        "streak": 0,
        "listed": false
      },
      {
        "id": "f7u4jbruamorekaw1",
        "english": "draw",
        "ukrainian": "малювати",
        "addedDate": "2026-05-04",
        "timesStudied": 14,
        "timesKnown": 9,
        "timesUnknown": 5,
        "category": "learning",
        "streak": 3
      },
      {
        "id": "lqjyhmnrvmorekaw1",
        "english": "sing",
        "ukrainian": "співати",
        "addedDate": "2026-05-04",
        "timesStudied": 15,
        "timesKnown": 9,
        "timesUnknown": 6,
        "category": "learning",
        "streak": 1
      },
      {
        "id": "71grepbubmorekaw1",
        "english": "use computer",
        "ukrainian": "використовувати компʼютер",
        "addedDate": "2026-05-04",
        "timesStudied": 13,
        "timesKnown": 10,
        "timesUnknown": 3,
        "category": "learning",
        "streak": 1
      },
      {
        "id": "xatt41lmemorka3b3",
        "english": "red",
        "ukrainian": "червоний",
        "addedDate": "2026-05-04",
        "timesStudied": 6,
        "timesKnown": 6,
        "timesUnknown": 0,
        "category": "learning",
        "streak": 6,
        "listed": false
      },
      {
        "id": "r2jvfm4e5morka3b3",
        "english": "blue",
        "ukrainian": "синій",
        "addedDate": "2026-05-04",
        "timesStudied": 7,
        "timesKnown": 6,
        "timesUnknown": 1,
        "category": "learning",
        "streak": 6
      },
      {
        "id": "2lgh02k68morka3b3",
        "english": "green",
        "ukrainian": "зелений",
        "addedDate": "2026-05-04",
        "timesStudied": 7,
        "timesKnown": 7,
        "timesUnknown": 0,
        "category": "learning",
        "streak": 6
      },
      {
        "id": "o4wgaejtnmorka3b3",
        "english": "yellow",
        "ukrainian": "жовтий",
        "addedDate": "2026-05-04",
        "timesStudied": 6,
        "timesKnown": 6,
        "timesUnknown": 0,
        "category": "learning",
        "streak": 6,
        "listed": false
      },
      {
        "id": "jxf2irbotmorka3b3",
        "english": "orange",
        "ukrainian": "помаранчевий",
        "addedDate": "2026-05-04",
        "timesStudied": 6,
        "timesKnown": 6,
        "timesUnknown": 0,
        "category": "learning",
        "streak": 6
      },
      {
        "id": "xiutznk0hmorka3b3",
        "english": "purple",
        "ukrainian": "фіолетовий",
        "addedDate": "2026-05-04",
        "timesStudied": 9,
        "timesKnown": 7,
        "timesUnknown": 2,
        "category": "learning",
        "streak": 5,
        "listed": false
      },
      {
        "id": "4fmzzn7ojmorka3b3",
        "english": "pink",
        "ukrainian": "рожевий",
        "addedDate": "2026-05-04",
        "timesStudied": 7,
        "timesKnown": 7,
        "timesUnknown": 0,
        "category": "learning",
        "streak": 6
      },
      {
        "id": "h3egpbpinmorka3b3",
        "english": "white",
        "ukrainian": "білий",
        "addedDate": "2026-05-04",
        "timesStudied": 6,
        "timesKnown": 6,
        "timesUnknown": 0,
        "category": "learning",
        "streak": 6
      },
      {
        "id": "7hup9f1onmorka3b3",
        "english": "black",
        "ukrainian": "чорний",
        "addedDate": "2026-05-04",
        "timesStudied": 7,
        "timesKnown": 6,
        "timesUnknown": 1,
        "category": "learning",
        "streak": 3
      },
      {
        "id": "fjbjwtb5cmorka3b3",
        "english": "brown",
        "ukrainian": "коричневий",
        "addedDate": "2026-05-04",
        "timesStudied": 9,
        "timesKnown": 6,
        "timesUnknown": 3,
        "category": "learning",
        "streak": 1
      },
      {
        "id": "1rwln4m30morka3b3",
        "english": "gray",
        "ukrainian": "сірий",
        "addedDate": "2026-05-04",
        "timesStudied": 16,
        "timesKnown": 7,
        "timesUnknown": 9,
        "category": "learning",
        "streak": 0,
        "listed": false
      },
      {
        "id": "cioz5n22omorkbqt3",
        "english": "bus",
        "ukrainian": "автобус",
        "addedDate": "2026-05-04",
        "timesStudied": 17,
        "timesKnown": 7,
        "timesUnknown": 10,
        "category": "hard",
        "streak": 2,
        "listed": true
      },
      {
        "id": "w9wk49it3morkbqt3",
        "english": "bicycle",
        "ukrainian": "велосипед",
        "addedDate": "2026-05-04",
        "timesStudied": 11,
        "timesKnown": 7,
        "timesUnknown": 4,
        "category": "learning",
        "streak": 0,
        "listed": true
      },
      {
        "id": "seb2j1nv5morkbqt3",
        "english": "walk",
        "ukrainian": "ходити",
        "addedDate": "2026-05-04",
        "timesStudied": 23,
        "timesKnown": 8,
        "timesUnknown": 15,
        "category": "hard",
        "streak": 2,
        "listed": true
      },
      {
        "id": "9u6su04t2morkbqt3",
        "english": "How many?",
        "ukrainian": "скільки",
        "addedDate": "2026-05-04",
        "timesStudied": 16,
        "timesKnown": 7,
        "timesUnknown": 9,
        "category": "hard",
        "streak": 2,
        "listed": true
      },
      {
        "id": "l21nc3gd9morkbqt3",
        "english": "children",
        "ukrainian": "діти(дітей)",
        "addedDate": "2026-05-04",
        "timesStudied": 18,
        "timesKnown": 7,
        "timesUnknown": 11,
        "category": "hard",
        "streak": 2,
        "listed": true
      },
      {
        "id": "uxeaadt8kmorkbqt3",
        "english": "you",
        "ukrainian": "ти",
        "addedDate": "2026-05-04",
        "timesStudied": 8,
        "timesKnown": 6,
        "timesUnknown": 2,
        "category": "learning",
        "streak": 0
      },
      {
        "id": "ejtenfo8pmorkbqt3",
        "english": "my",
        "ukrainian": "моє",
        "addedDate": "2026-05-04",
        "timesStudied": 8,
        "timesKnown": 6,
        "timesUnknown": 2,
        "category": "learning",
        "streak": 1
      },
      {
        "id": "lh9gd2eppmorkbqt3",
        "english": "name",
        "ukrainian": "імʼя",
        "addedDate": "2026-05-04",
        "timesStudied": 9,
        "timesKnown": 7,
        "timesUnknown": 2,
        "category": "learning",
        "streak": 1
      },
      {
        "id": "2xeouka9dmorkbqt3",
        "english": "choose",
        "ukrainian": "вибрати",
        "addedDate": "2026-05-04",
        "timesStudied": 16,
        "timesKnown": 8,
        "timesUnknown": 8,
        "category": "hard",
        "streak": 1,
        "listed": true
      },
      {
        "id": "skl2ypd6nmorkbqt3",
        "english": "word",
        "ukrainian": "слово",
        "addedDate": "2026-05-04",
        "timesStudied": 30,
        "timesKnown": 6,
        "timesUnknown": 24,
        "category": "hard",
        "streak": 0,
        "listed": false
      },
      {
        "id": "kc9hrh7u3morkbqt3",
        "english": "picture",
        "ukrainian": "картинка",
        "addedDate": "2026-05-04",
        "timesStudied": 18,
        "timesKnown": 7,
        "timesUnknown": 11,
        "category": "hard",
        "streak": 2
      },
      {
        "id": "esocn7lpwmoswk801",
        "english": "he",
        "ukrainian": "він",
        "addedDate": "2026-05-05",
        "timesStudied": 7,
        "timesKnown": 4,
        "timesUnknown": 3,
        "category": "learning",
        "streak": 2
      },
      {
        "id": "5yhd86lkxmoswkfqt",
        "english": "she",
        "ukrainian": "вона",
        "addedDate": "2026-05-05",
        "timesStudied": 11,
        "timesKnown": 5,
        "timesUnknown": 6,
        "category": "hard",
        "streak": 2,
        "listed": true
      },
      {
        "id": "zmyrijyb9moswl1d1",
        "english": "it",
        "ukrainian": "воно",
        "addedDate": "2026-05-05",
        "timesStudied": 12,
        "timesKnown": 4,
        "timesUnknown": 8,
        "category": "hard",
        "streak": 1
      },
      {
        "id": "qtvwl7civmovxz5op",
        "english": "we",
        "ukrainian": "ми",
        "addedDate": "2026-05-07",
        "timesStudied": 3,
        "timesKnown": 1,
        "timesUnknown": 2,
        "category": "hard",
        "streak": 0
      },
      {
        "id": "cgqa4w9jvmovxz5op",
        "english": "they",
        "ukrainian": "вони",
        "addedDate": "2026-05-07",
        "timesStudied": 9,
        "timesKnown": 1,
        "timesUnknown": 8,
        "category": "hard",
        "streak": 0
      },
      {
        "id": "uxas6a5btmovy08qb",
        "english": "please",
        "ukrainian": "будь ласка",
        "addedDate": "2026-05-07",
        "timesStudied": 1,
        "timesKnown": 1,
        "timesUnknown": 0,
        "category": "learning",
        "streak": 1
      },
      {
        "id": "gshf9kfktmovy1o8x",
        "english": "mother",
        "ukrainian": "мама",
        "addedDate": "2026-05-07",
        "timesStudied": 1,
        "timesKnown": 1,
        "timesUnknown": 0,
        "category": "learning",
        "streak": 1
      },
      {
        "id": "sdlwgrrz5movy1siu",
        "english": "father",
        "ukrainian": "тато",
        "addedDate": "2026-05-07",
        "timesStudied": 2,
        "timesKnown": 1,
        "timesUnknown": 1,
        "category": "learning",
        "streak": 0
      },
      {
        "id": "we6hnsob3movy1siu",
        "english": "brother",
        "ukrainian": "брат",
        "addedDate": "2026-05-07",
        "timesStudied": 1,
        "timesKnown": 1,
        "timesUnknown": 0,
        "category": "learning",
        "streak": 1
      },
      {
        "id": "qe5pr41ulmovy34bi",
        "english": "doll",
        "ukrainian": "лялька",
        "addedDate": "2026-05-07",
        "timesStudied": 1,
        "timesKnown": 1,
        "timesUnknown": 0,
        "category": "learning",
        "streak": 1
      },
      {
        "id": "g75jnyrs2movy3gnw",
        "english": "toy",
        "ukrainian": "іграшка",
        "addedDate": "2026-05-07",
        "timesStudied": 4,
        "timesKnown": 1,
        "timesUnknown": 3,
        "category": "hard",
        "streak": 0
      },
      {
        "id": "39nlelv1tmovy3tat",
        "english": "bag",
        "ukrainian": "сумка",
        "addedDate": "2026-05-07",
        "timesStudied": 2,
        "timesKnown": 1,
        "timesUnknown": 1,
        "category": "learning",
        "streak": 0
      },
      {
        "id": "p7a9okj5fmovy4jcv",
        "english": "bird",
        "ukrainian": "пташка",
        "addedDate": "2026-05-07",
        "timesStudied": 3,
        "timesKnown": 1,
        "timesUnknown": 2,
        "category": "hard",
        "streak": 0,
        "listed": false
      },
      {
        "id": "ytny0zb9lmovy4jcv",
        "english": "fish",
        "ukrainian": "риба",
        "addedDate": "2026-05-07",
        "timesStudied": 1,
        "timesKnown": 1,
        "timesUnknown": 0,
        "category": "learning",
        "streak": 1
      },
      {
        "id": "vinxoyfvhmovy4jcv",
        "english": "cow",
        "ukrainian": "корова",
        "addedDate": "2026-05-07",
        "timesStudied": 1,
        "timesKnown": 1,
        "timesUnknown": 0,
        "category": "learning",
        "streak": 1
      },
      {
        "id": "kmnn5pybsmovy5fp2",
        "english": "bread",
        "ukrainian": "хліб",
        "addedDate": "2026-05-07",
        "timesStudied": 3,
        "timesKnown": 2,
        "timesUnknown": 1,
        "category": "learning",
        "streak": 0
      },
      {
        "id": "t6ffxljqnmovy5fp2",
        "english": "milk",
        "ukrainian": "молоко",
        "addedDate": "2026-05-07",
        "timesStudied": 1,
        "timesKnown": 1,
        "timesUnknown": 0,
        "category": "learning",
        "streak": 1
      },
      {
        "id": "lx8n99mu9movy5rsw",
        "english": "juice",
        "ukrainian": "сік",
        "addedDate": "2026-05-07",
        "timesStudied": 1,
        "timesKnown": 1,
        "timesUnknown": 0,
        "category": "learning",
        "streak": 1
      }
    ],
    "sessions": [
      {
        "id": "fm0d52idgmor9mnaz",
        "date": "2026-05-04",
        "direction": "en-ua",
        "totalWords": 5,
        "knownFirst": 4,
        "duration": 66
      },
      {
        "id": "vx85e7qhnmordtto9",
        "date": "2026-05-04",
        "direction": "en-ua",
        "totalWords": 11,
        "knownFirst": 10,
        "duration": 180
      },
      {
        "id": "sweifzqnsmore0c1c",
        "date": "2026-05-04",
        "direction": "ua-en",
        "totalWords": 11,
        "knownFirst": 7,
        "duration": 174
      },
      {
        "id": "r0bs67tmtmorecttw",
        "date": "2026-05-04",
        "direction": "en-ua",
        "totalWords": 15,
        "knownFirst": 8,
        "duration": 353
      },
      {
        "id": "2ti6cqerrmorefx1l",
        "date": "2026-05-04",
        "direction": "ua-en",
        "totalWords": 15,
        "knownFirst": 14,
        "duration": 120
      },
      {
        "id": "o8ti0ep7kmorew1ky",
        "date": "2026-05-04",
        "direction": "en-ua",
        "totalWords": 21,
        "knownFirst": 17,
        "duration": 456
      },
      {
        "id": "6efx3vv8ymorjkl75",
        "date": "2026-05-04",
        "direction": "en-ua",
        "totalWords": 21,
        "knownFirst": 16,
        "duration": 629
      },
      {
        "id": "qq6zc1huymorjtf26",
        "date": "2026-05-04",
        "direction": "ua-en",
        "totalWords": 17,
        "knownFirst": 13,
        "duration": 390
      },
      {
        "id": "c4h3hvbq8morl680h",
        "date": "2026-05-04",
        "direction": "en-ua",
        "totalWords": 38,
        "knownFirst": 26,
        "duration": 1415
      },
      {
        "id": "0etzzxmdkmoswikra",
        "date": "2026-05-05",
        "direction": "ua-en",
        "totalWords": 44,
        "knownFirst": 22,
        "duration": 7636
      },
      {
        "id": "tr40ajwoomoszidjp",
        "date": "2026-05-05",
        "direction": "en-ua",
        "totalWords": 39,
        "knownFirst": 27,
        "duration": 677
      },
      {
        "id": "ggghuabnamou63d49",
        "date": "2026-05-06",
        "direction": "en-ua",
        "totalWords": 39,
        "knownFirst": 27,
        "duration": 1063
      },
      {
        "id": "xriaihyo7movxus6j",
        "date": "2026-05-07",
        "direction": "en-ua",
        "totalWords": 45,
        "knownFirst": 36,
        "duration": 107019
      },
      {
        "id": "6pkuppvnhmovxx5yv",
        "date": "2026-05-07",
        "direction": "en-ua",
        "totalWords": 11,
        "knownFirst": 9,
        "duration": 89
      },
      {
        "id": "f0tpgjv8omovyoz99",
        "date": "2026-05-07",
        "direction": "en-ua",
        "totalWords": 52,
        "knownFirst": 41,
        "duration": 708
      }
    ],
    "streak": 4,
    "bestStreak": 4,
    "lastStudied": "2026-05-07",
    "achievements": [
      "first_word",
      "first_session",
      "words_10",
      "sessions_5",
      "words_25",
      "sessions_3",
      "sessions_10",
      "streak_3",
      "words_50"
    ],
    "xp": 4989,
    "pinnedIds": []
  },
  {
    "id": "iqyi2j5a2motlqef3",
    "name": "Тімоха поляк",
    "avatar": "🏆",
    "color": "#FFC107",
    "isChild": true,
    "language": "pl",
    "words": [
      {
        "id": "k0xok9ejbmotoykgy",
        "english": "jabłko",
        "ukrainian": "яблуко",
        "addedDate": "2026-05-06",
        "timesStudied": 0,
        "timesKnown": 0,
        "timesUnknown": 0,
        "category": "learning",
        "streak": 0
      },
      {
        "id": "f9oit1q9mmotoykgy",
        "english": "kot",
        "ukrainian": "кіт",
        "addedDate": "2026-05-06",
        "timesStudied": 0,
        "timesKnown": 0,
        "timesUnknown": 0,
        "category": "learning",
        "streak": 0
      },
      {
        "id": "51tueywebmotoykgy",
        "english": "pies",
        "ukrainian": "собака",
        "addedDate": "2026-05-06",
        "timesStudied": 0,
        "timesKnown": 0,
        "timesUnknown": 0,
        "category": "learning",
        "streak": 0
      },
      {
        "id": "catytr73imotoykgy",
        "english": "dom",
        "ukrainian": "будинок",
        "addedDate": "2026-05-06",
        "timesStudied": 0,
        "timesKnown": 0,
        "timesUnknown": 0,
        "category": "learning",
        "streak": 0
      },
      {
        "id": "uwf3i7dkamotoykgy",
        "english": "woda",
        "ukrainian": "вода",
        "addedDate": "2026-05-06",
        "timesStudied": 0,
        "timesKnown": 0,
        "timesUnknown": 0,
        "category": "learning",
        "streak": 0
      },
      {
        "id": "niq7fs03ymotoykgy",
        "english": "mama",
        "ukrainian": "мама",
        "addedDate": "2026-05-06",
        "timesStudied": 0,
        "timesKnown": 0,
        "timesUnknown": 0,
        "category": "learning",
        "streak": 0
      },
      {
        "id": "1mueh9kqdmotoykgy",
        "english": "tata",
        "ukrainian": "тато",
        "addedDate": "2026-05-06",
        "timesStudied": 0,
        "timesKnown": 0,
        "timesUnknown": 0,
        "category": "learning",
        "streak": 0
      },
      {
        "id": "n21fl006gmotoykgy",
        "english": "szkoła",
        "ukrainian": "школа",
        "addedDate": "2026-05-06",
        "timesStudied": 0,
        "timesKnown": 0,
        "timesUnknown": 0,
        "category": "learning",
        "streak": 0
      },
      {
        "id": "zqh2ze77lmotoykgy",
        "english": "książka",
        "ukrainian": "книга",
        "addedDate": "2026-05-06",
        "timesStudied": 0,
        "timesKnown": 0,
        "timesUnknown": 0,
        "category": "learning",
        "streak": 0
      },
      {
        "id": "wcbgt9qexmotoykgy",
        "english": "słońce",
        "ukrainian": "сонце",
        "addedDate": "2026-05-06",
        "timesStudied": 0,
        "timesKnown": 0,
        "timesUnknown": 0,
        "category": "learning",
        "streak": 0
      },
      {
        "id": "fratyf2e5motoykgy",
        "english": "chleb",
        "ukrainian": "хліб",
        "addedDate": "2026-05-06",
        "timesStudied": 0,
        "timesKnown": 0,
        "timesUnknown": 0,
        "category": "learning",
        "streak": 0
      },
      {
        "id": "x9nlcnq8amotoykgy",
        "english": "mleko",
        "ukrainian": "молоко",
        "addedDate": "2026-05-06",
        "timesStudied": 0,
        "timesKnown": 0,
        "timesUnknown": 0,
        "category": "learning",
        "streak": 0
      },
      {
        "id": "25w1cene9motoykgy",
        "english": "ryba",
        "ukrainian": "риба",
        "addedDate": "2026-05-06",
        "timesStudied": 0,
        "timesKnown": 0,
        "timesUnknown": 0,
        "category": "learning",
        "streak": 0
      },
      {
        "id": "ms1eya3j8motoykgy",
        "english": "ptak",
        "ukrainian": "птах",
        "addedDate": "2026-05-06",
        "timesStudied": 1,
        "timesKnown": 1,
        "timesUnknown": 0,
        "category": "learning",
        "streak": 0
      },
      {
        "id": "47qt2si3zmotoykgy",
        "english": "drzewo",
        "ukrainian": "дерево",
        "addedDate": "2026-05-06",
        "timesStudied": 1,
        "timesKnown": 1,
        "timesUnknown": 0,
        "category": "learning",
        "streak": 0
      },
      {
        "id": "dqwurl0vwmotoykgy",
        "english": "kwiat",
        "ukrainian": "квітка",
        "addedDate": "2026-05-06",
        "timesStudied": 0,
        "timesKnown": 0,
        "timesUnknown": 0,
        "category": "learning",
        "streak": 0
      },
      {
        "id": "fkuym204gmotoykgy",
        "english": "miasto",
        "ukrainian": "місто",
        "addedDate": "2026-05-06",
        "timesStudied": 0,
        "timesKnown": 0,
        "timesUnknown": 0,
        "category": "learning",
        "streak": 0
      },
      {
        "id": "hwc9jmmgomotoykgy",
        "english": "rzeka",
        "ukrainian": "річка",
        "addedDate": "2026-05-06",
        "timesStudied": 0,
        "timesKnown": 0,
        "timesUnknown": 0,
        "category": "learning",
        "streak": 0
      },
      {
        "id": "4udkuvro5motoykgy",
        "english": "morze",
        "ukrainian": "море",
        "addedDate": "2026-05-06",
        "timesStudied": 0,
        "timesKnown": 0,
        "timesUnknown": 0,
        "category": "learning",
        "streak": 0
      },
      {
        "id": "5ogja6oe9motoykgy",
        "english": "śnieg",
        "ukrainian": "сніг",
        "addedDate": "2026-05-06",
        "timesStudied": 0,
        "timesKnown": 0,
        "timesUnknown": 0,
        "category": "learning",
        "streak": 0
      },
      {
        "id": "dgnlol2pkmotoykgy",
        "english": "deszcz",
        "ukrainian": "дощ",
        "addedDate": "2026-05-06",
        "timesStudied": 0,
        "timesKnown": 0,
        "timesUnknown": 0,
        "category": "learning",
        "streak": 0
      },
      {
        "id": "d1d7bh0uimotoykgy",
        "english": "wiatr",
        "ukrainian": "вітер",
        "addedDate": "2026-05-06",
        "timesStudied": 0,
        "timesKnown": 0,
        "timesUnknown": 0,
        "category": "learning",
        "streak": 0
      },
      {
        "id": "8obxgl1dvmotoykgy",
        "english": "ogień",
        "ukrainian": "вогонь",
        "addedDate": "2026-05-06",
        "timesStudied": 0,
        "timesKnown": 0,
        "timesUnknown": 0,
        "category": "learning",
        "streak": 0
      },
      {
        "id": "80ktj90uxmotoykgy",
        "english": "niebo",
        "ukrainian": "небо",
        "addedDate": "2026-05-06",
        "timesStudied": 0,
        "timesKnown": 0,
        "timesUnknown": 0,
        "category": "learning",
        "streak": 0
      },
      {
        "id": "wq8rgzrzzmotoykgy",
        "english": "przyjaciel",
        "ukrainian": "друг",
        "addedDate": "2026-05-06",
        "timesStudied": 0,
        "timesKnown": 0,
        "timesUnknown": 0,
        "category": "learning",
        "streak": 0
      },
      {
        "id": "93gqbh0vqmotoykgy",
        "english": "muzyka",
        "ukrainian": "музика",
        "addedDate": "2026-05-06",
        "timesStudied": 0,
        "timesKnown": 0,
        "timesUnknown": 0,
        "category": "learning",
        "streak": 0
      },
      {
        "id": "cg0dxi3wjmotoykgy",
        "english": "gra",
        "ukrainian": "гра",
        "addedDate": "2026-05-06",
        "timesStudied": 0,
        "timesKnown": 0,
        "timesUnknown": 0,
        "category": "learning",
        "streak": 0
      },
      {
        "id": "ttqsjrrv0motoykgy",
        "english": "koń",
        "ukrainian": "кінь",
        "addedDate": "2026-05-06",
        "timesStudied": 0,
        "timesKnown": 0,
        "timesUnknown": 0,
        "category": "learning",
        "streak": 0
      },
      {
        "id": "a3gm98dlpmotoykgy",
        "english": "krowа",
        "ukrainian": "корова",
        "addedDate": "2026-05-06",
        "timesStudied": 0,
        "timesKnown": 0,
        "timesUnknown": 0,
        "category": "learning",
        "streak": 0
      },
      {
        "id": "bupvur51xmotoykgy",
        "english": "niedźwiedź",
        "ukrainian": "ведмідь",
        "addedDate": "2026-05-06",
        "timesStudied": 0,
        "timesKnown": 0,
        "timesUnknown": 0,
        "category": "learning",
        "streak": 0
      },
      {
        "id": "o2v78iz3umotoykgy",
        "english": "wilk",
        "ukrainian": "вовк",
        "addedDate": "2026-05-06",
        "timesStudied": 0,
        "timesKnown": 0,
        "timesUnknown": 0,
        "category": "learning",
        "streak": 0
      },
      {
        "id": "w172r6xazmotoykgy",
        "english": "królik",
        "ukrainian": "кролик",
        "addedDate": "2026-05-06",
        "timesStudied": 0,
        "timesKnown": 0,
        "timesUnknown": 0,
        "category": "learning",
        "streak": 0
      },
      {
        "id": "fim6x56y9motoykgy",
        "english": "zamek",
        "ukrainian": "замок",
        "addedDate": "2026-05-06",
        "timesStudied": 0,
        "timesKnown": 0,
        "timesUnknown": 0,
        "category": "learning",
        "streak": 0
      },
      {
        "id": "0xcfv0aetmotoykgy",
        "english": "magia",
        "ukrainian": "магія",
        "addedDate": "2026-05-06",
        "timesStudied": 0,
        "timesKnown": 0,
        "timesUnknown": 0,
        "category": "learning",
        "streak": 0
      },
      {
        "id": "pxoiea9s6motoykgy",
        "english": "serce",
        "ukrainian": "серце",
        "addedDate": "2026-05-06",
        "timesStudied": 0,
        "timesKnown": 0,
        "timesUnknown": 0,
        "category": "learning",
        "streak": 0
      },
      {
        "id": "6focmo1s6motoykgy",
        "english": "ręka",
        "ukrainian": "рука",
        "addedDate": "2026-05-06",
        "timesStudied": 0,
        "timesKnown": 0,
        "timesUnknown": 0,
        "category": "learning",
        "streak": 0
      },
      {
        "id": "fqpnqsck7motoykgy",
        "english": "noga",
        "ukrainian": "нога",
        "addedDate": "2026-05-06",
        "timesStudied": 0,
        "timesKnown": 0,
        "timesUnknown": 0,
        "category": "learning",
        "streak": 0
      },
      {
        "id": "3v28ucbwomotoykgy",
        "english": "głowa",
        "ukrainian": "голова",
        "addedDate": "2026-05-06",
        "timesStudied": 0,
        "timesKnown": 0,
        "timesUnknown": 0,
        "category": "learning",
        "streak": 0
      },
      {
        "id": "m1hfqk66emotoykgy",
        "english": "oko",
        "ukrainian": "oko",
        "addedDate": "2026-05-06",
        "timesStudied": 0,
        "timesKnown": 0,
        "timesUnknown": 0,
        "category": "learning",
        "streak": 0
      },
      {
        "id": "cm5nht2j8motoykgy",
        "english": "ucho",
        "ukrainian": "вухо",
        "addedDate": "2026-05-06",
        "timesStudied": 0,
        "timesKnown": 0,
        "timesUnknown": 0,
        "category": "learning",
        "streak": 0
      }
    ],
    "sessions": [],
    "streak": 0,
    "bestStreak": 0,
    "lastStudied": null,
    "achievements": [],
    "xp": 10,
    "pinnedIds": [
      "0yifyu4yzmotlqef3"
    ]
  }
]